odoo8_addon_donation_direct_debit-8.0.0.1.0.99.dev3-py2.7-nspkg.pth
odoo8_addon_donation_direct_debit-8.0.0.1.0.99.dev3.dist-info/DESCRIPTION.rst
odoo8_addon_donation_direct_debit-8.0.0.1.0.99.dev3.dist-info/METADATA
odoo8_addon_donation_direct_debit-8.0.0.1.0.99.dev3.dist-info/RECORD
odoo8_addon_donation_direct_debit-8.0.0.1.0.99.dev3.dist-info/WHEEL
odoo8_addon_donation_direct_debit-8.0.0.1.0.99.dev3.dist-info/metadata.json
odoo8_addon_donation_direct_debit-8.0.0.1.0.99.dev3.dist-info/namespace_packages.txt
odoo8_addon_donation_direct_debit-8.0.0.1.0.99.dev3.dist-info/top_level.txt
odoo_addons/donation_direct_debit/README.rst
odoo_addons/donation_direct_debit/__init__.py
odoo_addons/donation_direct_debit/__openerp__.py
odoo_addons/donation_direct_debit/donation.py
odoo_addons/donation_direct_debit/donation_demo.xml
odoo_addons/donation_direct_debit/donation_view.xml
odoo_addons/donation_direct_debit/i18n/fr.po
odoo_addons/donation_direct_debit/security/ir.model.access.csv
odoo_addons/donation_direct_debit/static/description/icon.png
odoo_addons/donation_direct_debit/test/direct_debit.yml
